CHANGELOG.txt
DATASOURCE_README.md
LICENCE.txt
MANIFEST.in
README.md
README.txt
__init__.py
setup.py
acceldata_sdk/__init__.py
acceldata_sdk/api_version_utils.py
acceldata_sdk/client.py
acceldata_sdk/common.py
acceldata_sdk/constants.py
acceldata_sdk/datetime_utils.py
acceldata_sdk/errors.py
acceldata_sdk/initialiser.py
acceldata_sdk/time_range_utils.py
acceldata_sdk/torch_client.py
acceldata_sdk/torch_http_client.py
acceldata_sdk.egg-info/PKG-INFO
acceldata_sdk.egg-info/SOURCES.txt
acceldata_sdk.egg-info/dependency_links.txt
acceldata_sdk.egg-info/requires.txt
acceldata_sdk.egg-info/top_level.txt
acceldata_sdk/events/__init__.py
acceldata_sdk/events/generic_event.py
acceldata_sdk/events/job_events.py
acceldata_sdk/events/log_events.py
acceldata_sdk/events/span_event.py
acceldata_sdk/models/__init__.py
acceldata_sdk/models/asset.py
acceldata_sdk/models/assetType.py
acceldata_sdk/models/common_types.py
acceldata_sdk/models/connection.py
acceldata_sdk/models/create_asset.py
acceldata_sdk/models/datasource.py
acceldata_sdk/models/dqrule.py
acceldata_sdk/models/freshnessrule.py
acceldata_sdk/models/job.py
acceldata_sdk/models/pipeline.py
acceldata_sdk/models/profile.py
acceldata_sdk/models/reconcillationrule.py
acceldata_sdk/models/rule.py
acceldata_sdk/models/ruleExecutionResult.py
acceldata_sdk/models/span.py
acceldata_sdk/models/span_context.py
acceldata_sdk/models/tags.py
acceldata_sdk/models/threshold.py
docs/conf.py
docs/_build/html/_sources/index.rst.txt
docs/_build/html/_sources/modules.rst.txt
docs/_build/html/_sources/readme.rst.txt
docs/_build/html/_sources/readme_datasource.rst.txt
docs/_build/html/_sources/readme_pipeline.rst.txt
docs/_build/html/_sources/torch_sdk.events.rst.txt
docs/_build/html/_sources/torch_sdk.models.rst.txt
docs/_build/html/_sources/torch_sdk.rst.txt
integration_tests/test_commons.py
integration_tests/test_constants.py
integration_tests/test_ds_assets.py
integration_tests/test_external_integration_default_time.py
integration_tests/test_external_integration_explicit_time.py
integration_tests/test_freshness_policy.py
integration_tests/test_pipelines.py
integration_tests/test_policy.py
